wattslab_atlas/__init__.py
wattslab_atlas/auth.py
wattslab_atlas/client.py
wattslab_atlas/exceptions.py
wattslab_atlas/models.py
wattslab_atlas/storage.py
wattslab_atlas-1.2.0.dist-info/licenses/LICENSE
wattslab_atlas-1.2.0.dist-info/METADATA
wattslab_atlas-1.2.0.dist-info/WHEEL
wattslab_atlas-1.2.0.dist-info/top_level.txt
wattslab_atlas-1.2.0.dist-info/RECORD
