Metadata-Version: 2.4
Name: wattslab-atlas
Version: 1.2.0
Summary: Python SDK for Atlas API - A research cartography platform
Author-email: Amirhossein Nakhaei <your.email@example.com>
License: MIT
Project-URL: Homepage, https://github.com/Watts-Lab/atlas-sdk
Project-URL: Repository, https://github.com/Watts-Lab/atlas-sdk
Project-URL: Documentation, https://atlas-sdk.readthedocs.io
Keywords: atlas,api,sdk,research,papers
Classifier: Development Status :: 4 - Beta
Classifier: Intended Audience :: Developers
Classifier: License :: OSI Approved :: MIT License
Classifier: Programming Language :: Python :: 3
Classifier: Programming Language :: Python :: 3.9
Classifier: Programming Language :: Python :: 3.10
Classifier: Programming Language :: Python :: 3.11
Classifier: Programming Language :: Python :: 3.12
Requires-Python: >=3.9
License-File: LICENSE
Requires-Dist: requests>=2.31.0
Requires-Dist: types-requests>=2.31.0
Requires-Dist: pydantic>=2.0.0
Requires-Dist: python-dateutil>=2.8.2
Requires-Dist: keyring>=24.0.0
Requires-Dist: cryptography>=41.0.0
Requires-Dist: PyYAML>=6.0
Provides-Extra: dev
Requires-Dist: pytest>=7.4.0; extra == "dev"
Requires-Dist: pytest-cov>=4.1.0; extra == "dev"
Requires-Dist: black>=23.0.0; extra == "dev"
Requires-Dist: mypy>=1.5.0; extra == "dev"
Requires-Dist: types-requests>=2.31.0; extra == "dev"
Requires-Dist: jupyter>=1.0.0; extra == "dev"
Dynamic: license-file
